mroudai_django_subscriptions-0.1.0.dist-info/licenses/LICENSE
subscriptions/__init__.py
subscriptions/admin.py
subscriptions/apps.py
subscriptions/conf.py
subscriptions/models.py
subscriptions/selectors.py
subscriptions/services.py
subscriptions/migrations/0001_initial.py
subscriptions/migrations/__init__.py
subscriptions/tests/__init__.py
subscriptions/tests/settings.py
subscriptions/tests/test_subscriptions.py
subscriptions/tests/urls.py
mroudai_django_subscriptions-0.1.0.dist-info/METADATA
mroudai_django_subscriptions-0.1.0.dist-info/WHEEL
mroudai_django_subscriptions-0.1.0.dist-info/top_level.txt
mroudai_django_subscriptions-0.1.0.dist-info/RECORD
