Metadata-Version: 2.4
Name: mroudai-django-subscriptions
Version: 0.1.0
Summary: Plans, entitlements, and usage tracking for Django SaaS apps.
Author: Open Source
License: MIT
Project-URL: Homepage, https://github.com/Kevin-Oudai/django-subscription
Keywords: django,subscriptions,plans,saas,entitlements
Classifier: Framework :: Django
Classifier: Framework :: Django :: 4.2
Classifier: Framework :: Django :: 5.0
Classifier: License :: OSI Approved :: MIT License
Classifier: Programming Language :: Python
Classifier: Programming Language :: Python :: 3
Classifier: Programming Language :: Python :: 3.10
Classifier: Programming Language :: Python :: 3.11
Classifier: Programming Language :: Python :: 3.12
Requires-Python: >=3.10
License-File: LICENSE
Requires-Dist: django>=4.2
Dynamic: license-file
